{
    "id": "com.flutter.app.frontend",
    "version": "1.0.0",
    "vendor": "LG Electronics",
    "type": "native",
    "main": "frontend",
    "title": "Flutter frontend app",
    "icon": "icon.png",
    "iconColor": "#ffffff",
    "largeIcon": "icon.png",
    "handlesRelaunch": true,
    "visible": true,
    "defaultWindowType": "card",
    "trustLevel": "default",
    "resolution": "1920x1080",
    "locationHint":"west",
    "noSplashOnLaunch":true,
    "spinnerOnLaunch": false,
    "transparent":false,
    "uiRevision":2,
    "requiredPermissions": [
        "applications",
        "applications.launcher",
        "applications.operation",
        "settings",
        "system"
    ],
    "supportTouchMode": "full"
}
